RoboArt/RoboArt.py
RoboArt/__init__.py
RoboArt-0.1.3.dist-info/LICENSE.txt
RoboArt-0.1.3.dist-info/METADATA
RoboArt-0.1.3.dist-info/WHEEL
RoboArt-0.1.3.dist-info/top_level.txt
RoboArt-0.1.3.dist-info/RECORD
