Metadata-Version: 2.1
Name: RoboArt
Version: 0.1.3
Summary: A basic random avatar generator
Author: puang59
Author-email: puang59@proton.me
Keywords: python,avatar,roboart,random avatar,robohash,robots art
Classifier: Development Status :: 1 - Planning
Classifier: Intended Audience :: Developers
Classifier: Programming Language :: Python :: 3
Classifier: Operating System :: Unix
Classifier: Operating System :: MacOS :: MacOS X
Classifier: Operating System :: Microsoft :: Windows
License-File: LICENSE.txt
